aws_cis_assessment-1.0.3.post1.dist-info/licenses/LICENSE
aws_cis_assessment_deprecated/__init__.py
aws_cis_assessment-1.0.3.post1.dist-info/METADATA
aws_cis_assessment-1.0.3.post1.dist-info/WHEEL
aws_cis_assessment-1.0.3.post1.dist-info/entry_points.txt
aws_cis_assessment-1.0.3.post1.dist-info/top_level.txt
aws_cis_assessment-1.0.3.post1.dist-info/RECORD
