Metadata-Version: 2.4
Name: aws-cis-assessment
Version: 1.0.3.post1
Summary: ⚠️ DEPRECATED: This package has been renamed to aws-cis-controls-assessment
Author-email: AWS CIS Assessment Team <security@example.com>
Maintainer-email: AWS CIS Assessment Team <security@example.com>
License: MIT
Project-URL: Homepage, https://github.com/yourusername/aws-cis-assessment
Project-URL: Documentation, https://github.com/yourusername/aws-cis-assessment/blob/main/README.md
Project-URL: Repository, https://github.com/yourusername/aws-cis-assessment.git
Project-URL: New Package, https://pypi.org/project/aws-cis-controls-assessment/
Keywords: deprecated,aws,security,compliance,cis,controls,assessment
Classifier: Development Status :: 7 - Inactive
Classifier: Intended Audience :: System Administrators
Classifier: Intended Audience :: Information Technology
Classifier: License :: OSI Approved :: MIT License
Classifier: Operating System :: OS Independent
Classifier: Programming Language :: Python :: 3
Classifier: Programming Language :: Python :: 3.8
Classifier: Programming Language :: Python :: 3.9
Classifier: Programming Language :: Python :: 3.10
Classifier: Programming Language :: Python :: 3.11
Classifier: Programming Language :: Python :: 3.12
Classifier: Topic :: Security
Requires-Python: >=3.8
License-File: LICENSE
Requires-Dist: aws-cis-controls-assessment>=1.0.4
Dynamic: license-file
